followthemoney_predict/__init__.py
followthemoney_predict/cli.py
followthemoney_predict/dasklike.py
followthemoney_predict/util.py
followthemoney_predict/workflow.py
followthemoney_predict/data_sources/__init__.py
followthemoney_predict/data_sources/aleph.py
followthemoney_predict/data_sources/common.py
followthemoney_predict/data_sources/disk.py
followthemoney_predict/lib/__init__.py
followthemoney_predict/lib/vocabulary.py
followthemoney_predict/pipelines/__init__.py
followthemoney_predict/pipelines/xref/__init__.py
followthemoney_predict/pipelines/xref/cli.py
followthemoney_predict/pipelines/xref/data.py
followthemoney_predict/pipelines/xref/data_schema.py
followthemoney_predict/pipelines/xref/pipeline.py
followthemoney_predict/pipelines/xref/settings.py
followthemoney_predict/pipelines/xref/models/__init__.py
followthemoney_predict/pipelines/xref/models/util.py
followthemoney_predict/pipelines/xref/models/xref_ftm_model.py
followthemoney_predict/pipelines/xref/models/xref_gru.py
followthemoney_predict/pipelines/xref/models/xref_linear.py
followthemoney_predict/pipelines/xref/models/xref_model.py
followthemoney_predict/pipelines/xref/models/xref_torch_model.py
followthemoney_predict/pipelines/xref/models/xref_xgboost.py
followthemoney_predict-0.10.1.dist-info/LICENSE
followthemoney_predict-0.10.1.dist-info/METADATA
followthemoney_predict-0.10.1.dist-info/WHEEL
followthemoney_predict-0.10.1.dist-info/entry_points.txt
followthemoney_predict-0.10.1.dist-info/namespace_packages.txt
followthemoney_predict-0.10.1.dist-info/top_level.txt
followthemoney_predict-0.10.1.dist-info/RECORD
