Metadata-Version: 2.1
Name: followthemoney-predict
Version: 0.10.1
Summary: UNKNOWN
Home-page: https://github.com/alephdata/followthemoney-predict/
Author: Organized Crime and Corruption Reporting Project
Author-email: data@occrp.org
License: MIT
Platform: UNKNOWN
Requires-Dist: click (<8.0.0,>=7.1.2)
Requires-Dist: alephclient
Requires-Dist: followthemoney
Requires-Dist: gitpython (<4.0.0,>=3.1.8)
Requires-Dist: banal (<2.0.0,>=1.0.1)
Requires-Dist: tqdm (<5.0.0,>=4.49.0)
Requires-Dist: orjson (<4.0.0,>=3.3.1)
Requires-Dist: gcsfs (<1.0.0,>=0.7.1)
Requires-Dist: numpy (<2.0.0,>=1.14.5)
Requires-Dist: xgboost (<2.0.0,>=1.2.0)
Requires-Dist: scikit-learn (<1.0.0,>=0.23.2)
Requires-Dist: dask[bag,dataframe,distributed] (<3.0.0,>=2.27.0)
Requires-Dist: cachey (<1.0.0,>=0.2.1)
Requires-Dist: bokeh (<3.0.0,>=2.2.1)
Requires-Dist: pyarrow (<2.0.0,>=1.0.1)
Requires-Dist: torch (==1.6.0)
Requires-Dist: torchvision (==0.7.0)
